invenio_oarepo/__init__.py
invenio_oarepo/config.py
invenio_oarepo/current_api.py
invenio_oarepo/version.py
invenio_oarepo/views.py
invenio_oarepo/templates/invenio_oarepo/frontpage.html
invenio_oarepo/templates/invenio_oarepo/record.html
invenio_oarepo/translations/.gitkeep
invenio_oarepo-1.1.0.dist-info/AUTHORS.rst
invenio_oarepo-1.1.0.dist-info/LICENSE
invenio_oarepo-1.1.0.dist-info/METADATA
invenio_oarepo-1.1.0.dist-info/WHEEL
invenio_oarepo-1.1.0.dist-info/entry_points.txt
invenio_oarepo-1.1.0.dist-info/top_level.txt
invenio_oarepo-1.1.0.dist-info/RECORD
