Metadata-Version: 2.1
Name: invenio-oarepo
Version: 1.1.0
Summary: Open Access Repository for Invenio
Home-page: https://github.com/oarepo/invenio-oarepo
Author: Miroslav Bauer
Author-email: bauer@cesnet.cz
License: MIT
Keywords: invenio-oarepo oarepo Invenio
Platform: any
Classifier: Environment :: Web Environment
Classifier: Intended Audience :: Developers
Classifier: License :: OSI Approved :: MIT License
Classifier: Operating System :: OS Independent
Classifier: Programming Language :: Python
Classifier: Topic :: Internet :: WWW/HTTP :: Dynamic Content
Classifier: Topic :: Software Development :: Libraries :: Python Modules
Classifier: Programming Language :: Python :: 2
Classifier: Programming Language :: Python :: 2.7
Classifier: Programming Language :: Python :: 3
Classifier: Programming Language :: Python :: 3.5
Classifier: Development Status :: 4 - Beta
Requires-Dist: Flask-BabelEx (>=0.9.3)
Provides-Extra: deploy
Requires-Dist: this-is-just-a-library-install-oarepo-package-to-have-a-complete-repository-deployment (>=1.0.0) ; extra == 'deploy'
Provides-Extra: docs
Requires-Dist: Sphinx (>=1.5.1) ; extra == 'docs'
Provides-Extra: tests
Requires-Dist: check-manifest (>=0.25) ; extra == 'tests'
Requires-Dist: coverage (>=4.0) ; extra == 'tests'
Requires-Dist: isort (>=4.3.3) ; extra == 'tests'
Requires-Dist: pydocstyle (>=2.0.0) ; extra == 'tests'
Requires-Dist: pytest-cov (>=2.5.1) ; extra == 'tests'
Requires-Dist: pytest-pep8 (>=1.0.6) ; extra == 'tests'
Requires-Dist: Sphinx (>=1.5.1) ; extra == 'tests'
Requires-Dist: invenio[auth,base,elasticsearch6,metadata,postgresql] (~=3.1.1) ; extra == 'tests'
